XStatic_Jasmine-2.4.1.2-py3.5-nspkg.pth
xstatic/pkg/jasmine/__init__.py
xstatic/pkg/jasmine/data/boot.js
xstatic/pkg/jasmine/data/console.js
xstatic/pkg/jasmine/data/jasmine-html.js
xstatic/pkg/jasmine/data/jasmine.css
xstatic/pkg/jasmine/data/jasmine.js
xstatic/pkg/jasmine/data/jasmine_favicon.png
XStatic_Jasmine-2.4.1.2.dist-info/LICENSE
XStatic_Jasmine-2.4.1.2.dist-info/METADATA
XStatic_Jasmine-2.4.1.2.dist-info/WHEEL
XStatic_Jasmine-2.4.1.2.dist-info/namespace_packages.txt
XStatic_Jasmine-2.4.1.2.dist-info/top_level.txt
XStatic_Jasmine-2.4.1.2.dist-info/RECORD
