Metadata-Version: 2.1
Name: XStatic-Jasmine
Version: 2.4.1.2
Summary: Jasmine 2.4.1 (XStatic packaging standard)
Home-page: http://jasmine.github.io/
Maintainer: Radomir Dopieralski
Maintainer-email: openstack@sheep.art.pl
License: MIT
Keywords: jasmine xstatic
Platform: any
